cc/serializer/__init__.py
cc/serializer/buffer_serializer.py
cc/serializer/serializer.py
cc/serializer/socket_serializer.py
cc/serializer/uart_serializer.py
cc.serializer-2024.8.17.dist-info/LICENSE
cc.serializer-2024.8.17.dist-info/METADATA
cc.serializer-2024.8.17.dist-info/WHEEL
cc.serializer-2024.8.17.dist-info/top_level.txt
cc.serializer-2024.8.17.dist-info/RECORD
